[{"first_name":"Samuel","last_name":"Poland","email":"spoland0@ebay.com","gender":"Male","salary":24689734},
{"first_name":"Maurie","last_name":"Gonnet","email":"mgonnet1@histats.com","gender":"Male","salary":16683708},
{"first_name":"Aidan","last_name":"Roll","email":"aroll2@merriam-webster.com","gender":"Female","salary":93558741},
{"first_name":"Bearnard","last_name":"Lavington","email":"blavington3@scientificamerican.com","gender":"Male","salary":88847781},
{"first_name":"Anselm","last_name":"Bibb","email":"abibb4@stumbleupon.com","gender":"Male","salary":96119563},
{"first_name":"Bernadina","last_name":"Bradman","email":"bbradman5@facebook.com","gender":"Female","salary":10253011},
{"first_name":"Enrichetta","last_name":"Chawner","email":"echawner6@de.vu","gender":"Female","salary":77115125},
{"first_name":"Broderic","last_name":"John","email":"bjohn7@earthlink.net","gender":"Male","salary":49465498},
{"first_name":"Sal","last_name":"Pattenden","email":"spattenden8@google.ru","gender":"Female","salary":66665608},
{"first_name":"Regen","last_name":"Dabbes","email":"rdabbes9@google.cn","gender":"Male","salary":88592751}]